1             0 LOAD_CONST               0 (20)
              2 LOAD_CONST               1 (14)
              4 LOAD_CONST               2 (7)
              6 LOAD_CONST               3 (7)
              8 LOAD_CONST               4 (5)
             10 LOAD_CONST               5 (24)
             12 LOAD_CONST               6 (16)
             14 LOAD_CONST               7 (4)
             16 LOAD_CONST               8 (60)
             18 LOAD_CONST               9 (41)
             20 LOAD_CONST              10 (125)
             22 LOAD_CONST              11 (28)
             24 LOAD_CONST              12 (41)
             26 LOAD_CONST              13 (120)
             28 LOAD_CONST              14 (51)
             30 LOAD_CONST              15 (26)
             32 LOAD_CONST              16 (24)
             34 LOAD_CONST              17 (58)
             36 LOAD_CONST              18 (127)
             38 LOAD_CONST              19 (197)
             40 LOAD_CONST              20 (21)
             42 LOAD_CONST              21 (123)
             44 LOAD_CONST              22 (13)
             46 LOAD_CONST              23 (23)
             48 LOAD_CONST              24 (118)
             50 LOAD_CONST              25 (58)
             52 LOAD_CONST              26 (17)
             54 LOAD_CONST              27 (20)
             56 LOAD_CONST              28 (121)
             58 LOAD_CONST              29 (21)
             60 LOAD_CONST              30 (51)
             62 LOAD_CONST              31 (13)
             64 LOAD_CONST              32 (51)
             66 LOAD_CONST              33 (109)
             68 LOAD_CONST              34 (30)
             70 LOAD_CONST              35 (28)
             72 LOAD_CONST              36 (46)
             74 LOAD_CONST              37 (120)
             76 LOAD_CONST              38 (60)
             78 LOAD_CONST              39 (123)
             80 LOAD_CONST              40 (24)
             82 LOAD_CONST              41 (55)
             84 LOAD_CONST              42 (28)
             86 LOAD_CONST              43 (62)
             80 BUILD_LIST              40
             82 STORE_NAME               0 (encrypted_data)

  2          84 LOAD_CONST              40 ('G')
             86 STORE_NAME               1 (cipher_key)

  3          88 LOAD_CONST              41 ('`')
             90 LOAD_NAME                1 (cipher_key)
             92 BINARY_ADD
             94 STORE_NAME               1 (cipher_key)

  4          96 LOAD_NAME                1 (cipher_key)
             98 LOAD_CONST              42 ('P')
            100 BINARY_ADD
            102 STORE_NAME               1 (cipher_key)

  5         104 LOAD_NAME                1 (cipher_key)
            106 LOAD_CONST              43 ('C')
            108 BINARY_ADD
            110 STORE_NAME               1 (cipher_key)

  6         112 LOAD_NAME                1 (cipher_key)
            114 LOAD_CONST              44 ('L')
            116 BINARY_ADD
            118 STORE_NAME               1 (cipher_key)

  7         120 LOAD_NAME                1 (cipher_key)
            122 LOAD_CONST              45 ('L')
            124 BINARY_ADD
            126 STORE_NAME               1 (cipher_key)

  8         128 LOAD_NAME                1 (cipher_key)
            130 LOAD_CONST              46 ('_')
            132 BINARY_ADD
            134 STORE_NAME               1 (cipher_key)

  9         136 LOAD_NAME                1 (cipher_key)
            138 LOAD_CONST              47 ('J')
            140 BINARY_ADD
            142 STORE_NAME               1 (cipher_key)

 11         152 LOAD_CONST              52 (<code object <listcomp> at 0x7f704e8a4d40, file "secret.py", line 11>)
            154 LOAD_CONST              53 ('<listcomp>')
            156 MAKE_FUNCTION            0
            158 LOAD_NAME                1 (cipher_key)
            160 GET_ITER
            162 CALL_FUNCTION            1
            164 STORE_NAME               2 (key_bytes)

 13     >>  166 LOAD_NAME                3 (len)
            168 LOAD_NAME                2 (key_bytes)
            170 CALL_FUNCTION            1
            172 LOAD_NAME                3 (len)
            174 LOAD_NAME                0 (encrypted_data)
            176 CALL_FUNCTION            1
            178 COMPARE_OP               0 (<)
            180 POP_JUMP_IF_FALSE      194

 14         182 LOAD_NAME                2 (key_bytes)
            184 LOAD_METHOD              4 (extend)
            186 LOAD_NAME                2 (key_bytes)
            188 CALL_METHOD              1
            190 POP_TOP
            192 JUMP_ABSOLUTE          166

 17     >>  194 LOAD_CONST              54 (<code object <listcomp> at 0x7f704e8a4df0, file "secret.py", line 17>)
            196 LOAD_CONST              55 ('<listcomp>')
            198 MAKE_FUNCTION            0
            200 LOAD_NAME                5 (zip)
            202 LOAD_NAME                0 (encrypted_data)
            204 LOAD_NAME                2 (key_bytes)
            206 CALL_FUNCTION            2
            208 GET_ITER
            210 CALL_FUNCTION            1
            212 STORE_NAME               6 (xor_result)

 19         214 LOAD_CONST              56 ('')
            216 LOAD_METHOD              7 (join)
            218 LOAD_NAME                8 (map)
            220 LOAD_NAME                9 (chr)
            222 LOAD_NAME                6 (xor_result)
            224 CALL_FUNCTION            2
            226 CALL_METHOD              1
            228 STORE_NAME              10 (intermediate_flag)

 21         230 LOAD_CONST              57 (<code object <listcomp> at 0x7f704e8a5040, file "secret.py", line 21>)
            232 LOAD_CONST              58 ('<listcomp>')
            234 MAKE_FUNCTION            0
            236 LOAD_NAME               10 (intermediate_flag)
            238 GET_ITER
            240 CALL_FUNCTION            1
            242 STORE_NAME              11 (decoded_chars)

 23         244 LOAD_CONST              56 ('')
            246 LOAD_METHOD              7 (join)
            248 LOAD_NAME               11 (decoded_chars)
            250 CALL_METHOD              1
            252 STORE_NAME              12 (final_flag)
            254 LOAD_CONST              59 (None)
            256 RETURN_VALUE

Disassembly of <code object <listcomp> at 0x7f704e8a4d40, file "secret.py", line 11>:
 11           0 BUILD_LIST               0
              2 LOAD_FAST                0 (.0)
        >>    4 FOR_ITER                16 (to 22)
              6 STORE_FAST               1 (char)
              8 LOAD_GLOBAL              0 (ord)
             10 LOAD_FAST                1 (char)
             12 LOAD_CONST               0 (1)
             14 BINARY_SUBTRACT
             16 LOAD_CONST               1 (7)
             18 BINARY_XOR
             20 CALL_FUNCTION            1
             22 LIST_APPEND              2
             24 JUMP_ABSOLUTE            4
        >>   26 RETURN_VALUE

Disassembly of <code object <listcomp> at 0x7f704e8a4df0, file "secret.py", line 17>:
 17           0 BUILD_LIST               0
              2 LOAD_FAST                0 (.0)
        >>    4 FOR_ITER                16 (to 22)
              6 UNPACK_SEQUENCE          2
              8 STORE_FAST               1 (a)
             10 STORE_FAST               2 (b)
             12 LOAD_FAST                1 (a)
             14 LOAD_FAST                2 (b)
             16 BINARY_XOR
             18 LIST_APPEND              2
             20 JUMP_ABSOLUTE            4
        >>   22 RETURN_VALUE

Disassembly of <code object <listcomp> at 0x7f704e8a5040, file "secret.py", line 21>:
 21           0 BUILD_LIST               0
              2 LOAD_FAST                0 (.0)
        >>    4 FOR_ITER                20 (to 26)
              6 STORE_FAST               1 (char)
              8 LOAD_GLOBAL              0 (ord)
             10 LOAD_FAST                1 (char)
             12 CALL_FUNCTION            1
             14 LOAD_CONST               0 (1)
             16 BINARY_SUBTRACT
             18 LOAD_CONST               1 (7)
             20 BINARY_XOR
             22 LOAD_GLOBAL              1 (chr)
             24 CALL_FUNCTION            1
             26 LIST_APPEND              2
             28 JUMP_ABSOLUTE            4
        >>   30 RETURN_VALUE